{
  "sections": {
    "slideshow": {
      "type": "slideshow",
      "blocks": {
        "slide-1": {
          "type": "image",
          "settings": {
            "image": "shopify:\/\/shop_images\/home-slide-tea-spoons-snow-loose-leaf-tea-desktop.jpg",
            "mobile_image": "shopify:\/\/shop_images\/home-slide-tea-spoons-snow-loose-leaf-tea-mobile-2.jpg",
            "text_position": "middle_left",
            "subheading": "warm up with",
            "title": "winter sips",
            "button_1_text": "winter teas",
            "button_1_link": "shopify:\/\/collections\/winter-teas",
            "button_2_text": "",
            "button_2_link": "",
            "text_color": "{{ shop.brand.colors.primary[0].background }}",
            "button_background": "#000000",
            "button_text_color": "#ffffff",
            "overlay_color": "{{ shop.brand.colors.primary[0].foreground }}",
            "overlay_opacity": 0
          }
        },
        "slide-2": {
          "type": "image",
          "settings": {
            "image": "shopify:\/\/shop_images\/home-slide-honey-bee-gift-box-sampler-desktop.jpg",
            "mobile_image": "shopify:\/\/shop_images\/home-slide-honey-bee-gift-box-sampler-mobile.jpg",
            "text_position": "middle_left",
            "subheading": "self care essentials",
            "title": "honey bee box",
            "button_1_text": "Learn more",
            "button_1_link": "shopify:\/\/products\/honey-bee-gift-box",
            "button_2_text": "",
            "button_2_link": "",
            "text_color": "{{ shop.brand.colors.primary[0].background }}",
            "button_background": "#000000",
            "button_text_color": "#ffffff",
            "overlay_color": "{{ shop.brand.colors.primary[0].foreground }}",
            "overlay_opacity": 0
          }
        }
      },
      "block_order": [
        "slide-1",
        "slide-2"
      ],
      "settings": {
        "section_height": "auto",
        "transition_type": "sweep",
        "autoplay": true,
        "cycle_speed": 8,
        "background": "rgba(0,0,0,0)"
      }
    },
    "6025d5dd-11f6-4063-8a61-4bb1c85be635": {
      "type": "image-with-text-overlay",
      "settings": {
        "reveal_on_scroll": true,
        "section_height": "auto",
        "image": "shopify:\/\/shop_images\/bwtt_tea_stain_on_paper.jpg",
        "subheading": "our ethos is our responsibility",
        "title": "to our planet",
        "content": "<p>Plastic is jamming up our water ways and threatening our environment. We offer organic loose leaf tea, compostable teabags, and compostable packaging.<\/p>",
        "button_text": "LEARN ABOUT US",
        "button_link": "shopify:\/\/pages\/about-us",
        "link_style": "button",
        "background_type": "full_width",
        "text_width": "small",
        "text_position": "middle_left",
        "text_color": "{{ shop.brand.colors.primary[0].background }}",
        "button_background": "#ffffff",
        "button_text_color": "#000000",
        "overlay_color": "#000000",
        "overlay_opacity": 0
      }
    },
    "564297e4-b25e-482c-b716-4cccb54374f6": {
      "type": "image-with-text",
      "disabled": true,
      "blocks": {
        "template--15665624809627__564297e4-b25e-482c-b716-4cccb54374f6-16696758759c383f6f-0": {
          "type": "item",
          "settings": {
            "image": "shopify:\/\/shop_images\/bwtt_laurel_ring_white_afb71a81-2657-4069-9e9a-64162ab4b846.png",
            "tab_label": "Item",
            "subheading": "our ethos is our responsibility",
            "title": "to our planet",
            "content": "<p>Plastic is jamming up our water ways and threatening our environment. We offer organic loose leaf tea, compostable teabags, and compostable packaging.<\/p>",
            "button_text": "Learn about us",
            "button_link": "shopify:\/\/pages\/about-us"
          }
        }
      },
      "block_order": [
        "template--15665624809627__564297e4-b25e-482c-b716-4cccb54374f6-16696758759c383f6f-0"
      ],
      "settings": {
        "reveal_on_scroll": true,
        "background_type": "full_width",
        "background_overlap": "both",
        "image_position": "right",
        "text_alignment": "left",
        "cycle_speed": 8,
        "accent_background": "{{ shop.brand.colors.primary[0].background }}",
        "text_color": "{{ shop.brand.colors.primary[0].foreground }}",
        "button_background": "{{ shop.brand.colors.primary[0].foreground }}",
        "button_text_color": "{{ shop.brand.colors.primary[0].background }}"
      }
    },
    "featured-collections": {
      "type": "featured-collections",
      "blocks": {
        "3a4f914c-3d13-4bf8-a2e0-9a505c0e8cd0": {
          "type": "collection",
          "settings": {
            "collection": "starter-teas",
            "label": "Starter teas",
            "button_text": "starter teas",
            "button_url": ""
          }
        },
        "collection-1": {
          "type": "collection",
          "settings": {
            "collection": "staff-picks",
            "label": "Staff Picks",
            "button_text": "Staff Picks",
            "button_url": ""
          }
        },
        "348a9fc8-cde7-4c02-8f7e-bd1222b03862": {
          "type": "collection",
          "settings": {
            "collection": "tea-essentials",
            "label": "Tea Essentials",
            "button_text": "Tea Essentials",
            "button_url": ""
          }
        }
      },
      "block_order": [
        "3a4f914c-3d13-4bf8-a2e0-9a505c0e8cd0",
        "collection-1",
        "348a9fc8-cde7-4c02-8f7e-bd1222b03862"
      ],
      "settings": {
        "subheading": "get to know",
        "title": "our teas",
        "content": "",
        "products_count": 4,
        "products_per_row": 6,
        "stack_products": true,
        "show_cta": false,
        "background": "rgba(0,0,0,0)",
        "text_color": "rgba(0,0,0,0)",
        "button_background": "rgba(0,0,0,0)",
        "button_text_color": "rgba(0,0,0,0)"
      }
    },
    "image-with-text-block": {
      "type": "image-with-text-block",
      "settings": {
        "reveal_on_scroll": true,
        "image": "shopify:\/\/shop_images\/Screen_Shot_2022-11-11_at_1.57.11_PM.png",
        "subheading": "WHOLESALE + PRIVATE LABELS",
        "title": "LEARN MORE ABOUT WHOLESALE",
        "content": "<p><strong>We love to collaborate.<\/strong> Whether with wholesale partnerships, private labels, custom blends, or simply for a special event in your life.<\/p>",
        "button_text": "Collaborate with us",
        "button_link": "shopify:\/\/pages\/wholesale",
        "background_type": "full_width",
        "text_position": "left",
        "text_alignment": "left",
        "text_background": "rgba(0,0,0,0)",
        "text_color": "rgba(0,0,0,0)",
        "button_background": "rgba(0,0,0,0)",
        "button_text_color": "rgba(0,0,0,0)"
      }
    },
    "87945452-155b-428a-9542-36ceb70a6a9e": {
      "type": "logo-list",
      "blocks": {
        "template--15665624809627__87945452-155b-428a-9542-36ceb70a6a9e-1667266268816b9f14-3": {
          "type": "logo",
          "settings": {
            "logo": "shopify:\/\/shop_images\/proudly-serving-logo_los_poblanos_eaf4dd7d-19cd-4426-8d8f-a99b310b9ef3.jpg",
            "link": "https:\/\/lospoblanos.com\/"
          }
        },
        "template--15665624809627__87945452-155b-428a-9542-36ceb70a6a9e-1667266268816b9f14-0": {
          "type": "logo",
          "settings": {
            "logo": "shopify:\/\/shop_images\/proudly-serving-logo_los_ojos.jpg",
            "link": "https:\/\/ojosparesorts.com\/"
          }
        },
        "template--15665624809627__87945452-155b-428a-9542-36ceb70a6a9e-1667266268816b9f14-1": {
          "type": "logo",
          "settings": {
            "logo": "shopify:\/\/shop_images\/proudly-serving-logo_moon_unit.jpg",
            "link": "shopify:\/\/pages\/moon-unit"
          }
        },
        "template--15665624809627__87945452-155b-428a-9542-36ceb70a6a9e-1667266268816b9f14-2": {
          "type": "logo",
          "settings": {
            "logo": "shopify:\/\/shop_images\/proudly-serving-logo_bishops_lodge.jpg",
            "link": "https:\/\/aubergeresorts.com\/bishopslodge\/"
          }
        },
        "template--15665624809627__87945452-155b-428a-9542-36ceb70a6a9e-1667266268816b9f14-5": {
          "type": "logo",
          "settings": {
            "logo": "shopify:\/\/shop_images\/proudly-serving-logomeow_wolf.jpg",
            "link": "https:\/\/meowwolf.com\/"
          }
        }
      },
      "block_order": [
        "template--15665624809627__87945452-155b-428a-9542-36ceb70a6a9e-1667266268816b9f14-3",
        "template--15665624809627__87945452-155b-428a-9542-36ceb70a6a9e-1667266268816b9f14-0",
        "template--15665624809627__87945452-155b-428a-9542-36ceb70a6a9e-1667266268816b9f14-1",
        "template--15665624809627__87945452-155b-428a-9542-36ceb70a6a9e-1667266268816b9f14-2",
        "template--15665624809627__87945452-155b-428a-9542-36ceb70a6a9e-1667266268816b9f14-5"
      ],
      "settings": {
        "reveal_on_scroll": true,
        "subheading": "business we are",
        "title": "PROUDLY SERVING",
        "button_text": "",
        "button_link": "",
        "stack_logos": true,
        "background": "rgba(0,0,0,0)",
        "text_color": "rgba(0,0,0,0)",
        "button_background": "rgba(0,0,0,0)",
        "button_text_color": "rgba(0,0,0,0)",
        "logo_background": "rgba(0,0,0,0)"
      }
    },
    "shop-the-look": {
      "type": "shop-the-look",
      "disabled": true,
      "blocks": {
        "look-1": {
          "type": "look",
          "settings": {
            "dot_type": "inverted",
            "product_1": "",
            "product_1_horizontal_position": 41,
            "product_1_vertical_position": 41,
            "product_1_horizontal_position_mobile": 30,
            "product_1_vertical_position_mobile": 30,
            "product_2": "",
            "product_2_horizontal_position": 46,
            "product_2_vertical_position": 64,
            "product_2_horizontal_position_mobile": 50,
            "product_2_vertical_position_mobile": 50,
            "product_3": "",
            "product_3_horizontal_position": 62,
            "product_3_vertical_position": 50,
            "product_3_horizontal_position_mobile": 70,
            "product_3_vertical_position_mobile": 70
          }
        },
        "0a3a942f-c21e-47b8-93fa-bac7260a82aa": {
          "type": "look",
          "settings": {
            "dot_type": "normal",
            "product_1": "",
            "product_1_horizontal_position": 30,
            "product_1_vertical_position": 30,
            "product_1_horizontal_position_mobile": 30,
            "product_1_vertical_position_mobile": 30,
            "product_2": "",
            "product_2_horizontal_position": 50,
            "product_2_vertical_position": 50,
            "product_2_horizontal_position_mobile": 50,
            "product_2_vertical_position_mobile": 50,
            "product_3": "",
            "product_3_horizontal_position": 70,
            "product_3_vertical_position": 70,
            "product_3_horizontal_position_mobile": 70,
            "product_3_vertical_position_mobile": 70
          }
        }
      },
      "block_order": [
        "look-1",
        "0a3a942f-c21e-47b8-93fa-bac7260a82aa"
      ],
      "settings": {
        "reveal_on_scroll": true,
        "label": "Shop the looks"
      }
    },
    "image-with-text": {
      "type": "image-with-text",
      "disabled": true,
      "blocks": {
        "item-1": {
          "type": "item",
          "settings": {
            "tab_label": "Text 1",
            "subheading": "Subheading",
            "title": "Image with text",
            "content": "<p>Use image with text to give your customers insight into your brand. Select imagery and text that relates to your style and story.<\/p>",
            "button_text": "",
            "button_link": ""
          }
        },
        "item-2": {
          "type": "item",
          "settings": {
            "tab_label": "Text 2",
            "subheading": "Subheading",
            "title": "Image with text",
            "content": "<p>Use image with text to give your customers insight into your brand. Select imagery and text that relates to your style and story.<\/p>",
            "button_text": "",
            "button_link": ""
          }
        }
      },
      "block_order": [
        "item-1",
        "item-2"
      ],
      "settings": {
        "reveal_on_scroll": true,
        "background_type": "full_width",
        "background_overlap": "image",
        "image_position": "left",
        "text_alignment": "center",
        "cycle_speed": 8,
        "accent_background": "rgba(0,0,0,0)",
        "text_color": "rgba(0,0,0,0)",
        "button_background": "rgba(0,0,0,0)",
        "button_text_color": "rgba(0,0,0,0)"
      }
    },
    "166853680447776749": {
      "type": "apps",
      "blocks": {
        "0fa2cd38-1156-4d05-9fac-46e6af4cc2ee": {
          "type": "shopify:\/\/apps\/instafeed-instagram-feed\/blocks\/app-block\/c447db20-095d-4a10-9725-b5977662c9d5",
          "settings": {
            "heading_size": 20,
            "feed_width": 100,
            "html_area": ""
          }
        }
      },
      "block_order": [
        "0fa2cd38-1156-4d05-9fac-46e6af4cc2ee"
      ],
      "settings": {
        "include_horizontal_margins": true,
        "include_vertical_margins": true
      }
    },
    "testimonials": {
      "type": "testimonials",
      "blocks": {
        "testimonial-1": {
          "type": "testimonial",
          "settings": {
            "content": "dana's tea is to die for. what a storied history tea has! so many health benefits! if you aren't already a tea lover you will be!",
            "author": "happy facebook customer"
          }
        },
        "a2c5cc81-a324-4a30-b3e1-2164e16b2c11": {
          "type": "testimonial",
          "settings": {
            "content": "wonderful shop! friendly, helpful, knowledgeable staff incredible tea. my personal favorite is high desert sage - it truly is taos in a cup.",
            "author": "google review"
          }
        }
      },
      "block_order": [
        "testimonial-1",
        "a2c5cc81-a324-4a30-b3e1-2164e16b2c11"
      ],
      "settings": {
        "reveal_on_scroll": true,
        "subheading": "",
        "title": "",
        "background": "rgba(0,0,0,0)",
        "text_color": "rgba(0,0,0,0)"
      }
    },
    "4d8454e3-ec51-4b26-a644-e17d7e9c87a1": {
      "type": "image-with-text-block",
      "settings": {
        "reveal_on_scroll": true,
        "image": "shopify:\/\/shop_images\/tog.jpg",
        "subheading": "a little",
        "title": "Taos tea shop",
        "content": "<p>Visit us at our shop at down Kit Carson road, just off the Taos Plaza at<br\/> <a href=\"https:\/\/www.google.com\/maps\/dir\/\/125+Kit+Carson+Rd,+Taos,+NM+87571\/@36.4066793,-105.6420144,12z\/data=!3m1!4b1!4m8!4m7!1m0!1m5!1m1!1s0x87176522b1249af9:0x7b8e4c7db143ba8a!2m2!1d-105.5719743!2d36.4066997\" target=\"_blank\" title=\"https:\/\/www.google.com\/maps\/dir\/\/125+Kit+Carson+Rd,+Taos,+NM+87571\/@36.4066793,-105.6420144,12z\/data=!3m1!4b1!4m8!4m7!1m0!1m5!1m1!1s0x87176522b1249af9:0x7b8e4c7db143ba8a!2m2!1d-105.5719743!2d36.4066997\">125 Kit Carson Rd, Taos, NM 87571<\/a>.<\/p><p>We're open Monday through Saturday from <strong>11am to 5pm<\/strong>. <em>We're closed on Sundays.<\/em><\/p>",
        "button_text": "Get directions",
        "button_link": "https:\/\/www.google.com\/maps\/dir\/\/125+Kit+Carson+Rd,+Taos,+NM+87571\/@36.4066793,-105.6420144,12z\/data=!3m1!4b1!4m8!4m7!1m0!1m5!1m1!1s0x87176522b1249af9:0x7b8e4c7db143ba8a!2m2!1d-105.5719743!2d36.4066997",
        "background_type": "full_width",
        "text_position": "left",
        "text_alignment": "left",
        "text_background": "rgba(0,0,0,0)",
        "text_color": "rgba(0,0,0,0)",
        "button_background": "rgba(0,0,0,0)",
        "button_text_color": "rgba(0,0,0,0)"
      }
    }
  },
  "order": [
    "slideshow",
    "6025d5dd-11f6-4063-8a61-4bb1c85be635",
    "564297e4-b25e-482c-b716-4cccb54374f6",
    "featured-collections",
    "image-with-text-block",
    "87945452-155b-428a-9542-36ceb70a6a9e",
    "shop-the-look",
    "image-with-text",
    "166853680447776749",
    "testimonials",
    "4d8454e3-ec51-4b26-a644-e17d7e9c87a1"
  ]
}